Metadata-Version: 2.1
Name: hnn
Version: 0.0.3.3
Summary: A programming framework based on PyTorch for hybrid neural networks with automatic quantization
Home-page: https://github.com/openBII/HNN
Author: Huanyu
Author-email: huanyu.qu@hotmail.com
License: Apache License 2.0
Keywords: hybrid neural networks,spiking neural networks,quantization
Platform: any
License-File: LICENSE
